alchetools/DbTools.py
alchetools/__init__.py
alchetools/uilts/__init__.py
alchetools/uilts/customize_logs.py
alchetools/uilts/time_utils.py
alchetools-0.1.3.dist-info/METADATA
alchetools-0.1.3.dist-info/RECORD
alchetools-0.1.3.dist-info/WHEEL
alchetools-0.1.3.dist-info/top_level.txt
