Metadata-Version: 2.1
Name: alchetools
Version: 0.1.3
Summary: A lightweight CRUD toolkit built on SQLAlchemy 2.x.
Home-page: https://github.com/yourusername/alchetools
Author: LiuZongxin
Author-email: Liu_zongxin@yeah.net
License: UNKNOWN
Platform: UNKNOWN
Classifier: Programming Language :: Python :: 3
Classifier: License :: OSI Approved :: MIT License
Classifier: Operating System :: OS Independent
Requires-Python: >=3.8
Requires-Dist: SQLAlchemy (>=2.0.29)
